trulens_eval/Example_TruBot.py
trulens_eval/LICENSE
trulens_eval/Leaderboard.py
trulens_eval/__init__.py
trulens_eval/app.py
trulens_eval/appui.py
trulens_eval/generate_test_set.py
trulens_eval/instruments.py
trulens_eval/keys.py
trulens_eval/requirements.optional.txt
trulens_eval/requirements.txt
trulens_eval/tru.py
trulens_eval/tru_basic_app.py
trulens_eval/tru_chain.py
trulens_eval/tru_custom_app.py
trulens_eval/tru_llama.py
trulens_eval/tru_rails.py
trulens_eval/tru_virtual.py
trulens_eval/database/__init__.py
trulens_eval/database/base.py
trulens_eval/database/exceptions.py
trulens_eval/database/orm.py
trulens_eval/database/sqlalchemy.py
trulens_eval/database/utils.py
trulens_eval/database/legacy/migration.py
trulens_eval/database/migrations/__init__.py
trulens_eval/database/migrations/alembic.ini
trulens_eval/database/migrations/data.py
trulens_eval/database/migrations/env.py
trulens_eval/database/migrations/versions/1_first_revision.py
trulens_eval/feedback/__init__.py
trulens_eval/feedback/embeddings.py
trulens_eval/feedback/feedback.py
trulens_eval/feedback/groundtruth.py
trulens_eval/feedback/prompts.py
trulens_eval/feedback/provider/__init__.py
trulens_eval/feedback/provider/base.py
trulens_eval/feedback/provider/bedrock.py
trulens_eval/feedback/provider/hugs.py
trulens_eval/feedback/provider/langchain.py
trulens_eval/feedback/provider/litellm.py
trulens_eval/feedback/provider/openai.py
trulens_eval/feedback/provider/endpoint/__init__.py
trulens_eval/feedback/provider/endpoint/base.py
trulens_eval/feedback/provider/endpoint/bedrock.py
trulens_eval/feedback/provider/endpoint/hugs.py
trulens_eval/feedback/provider/endpoint/langchain.py
trulens_eval/feedback/provider/endpoint/litellm.py
trulens_eval/feedback/provider/endpoint/openai.py
trulens_eval/feedback/v2/feedback.py
trulens_eval/feedback/v2/provider/base.py
trulens_eval/pages/Apps.py
trulens_eval/pages/Evaluations.py
trulens_eval/react_components/record_viewer/__init__.py
epinzur_trulens_eval-0.30.1b0.dist-info/METADATA
epinzur_trulens_eval-0.30.1b0.dist-info/WHEEL
epinzur_trulens_eval-0.30.1b0.dist-info/entry_points.txt
epinzur_trulens_eval-0.30.1b0.dist-info/top_level.txt
epinzur_trulens_eval-0.30.1b0.dist-info/RECORD
