Metadata-Version: 2.1
Name: epinzur_trulens_eval
Version: 0.30.1b0
Summary: Library to systematically track and evaluate LLM based applications.
Home-page: https://www.trulens.org
Author: Truera Inc
Author-email: all@truera.com
License: MIT
Classifier: Programming Language :: Python :: 3
Classifier: Operating System :: OS Independent
Classifier: Development Status :: 3 - Alpha
Classifier: License :: OSI Approved :: MIT License
Requires-Python: >= 3.8, < 3.13
Requires-Dist: numpy >=1.23.5
Requires-Dist: frozendict >=2.3.8
Requires-Dist: munch >=3.0.0
Requires-Dist: dill >=0.3.7
Requires-Dist: tqdm >=4.66.1
Requires-Dist: nltk >=3.8.1
Requires-Dist: requests >=2.31.0
Requires-Dist: nest-asyncio >=1.5.8
Requires-Dist: typing-extensions >=4.9.0
Requires-Dist: psutil >=5.9.8
Requires-Dist: pip >=24.0
Requires-Dist: packaging >=23.2
Requires-Dist: python-dotenv >=1.0.0
Requires-Dist: pydantic <3,>=2
Requires-Dist: merkle-json >=1.0.0
Requires-Dist: langchain >=0.1.14
Requires-Dist: langchain-core >=0.1.6
Requires-Dist: langchain-community >=0.0.38
Requires-Dist: typing-inspect >=0.8.0
Requires-Dist: millify >=0.1.1
Requires-Dist: humanize >=4.6.0
Requires-Dist: streamlit >=1.32.2
Requires-Dist: streamlit-aggrid ==0.3.4
Requires-Dist: streamlit-extras >=0.4.0
Requires-Dist: streamlit-pills >=0.3.0
Requires-Dist: rich >=13.6.0
Requires-Dist: sqlalchemy >=2.0.19
Requires-Dist: alembic >=1.11.2
